orquestra/__init__.py
orquestra/accountadapter.py
orquestra/apps.py
orquestra/apps_manager.py
orquestra/default_app.py
orquestra/settings.py
orquestra/urls.py
orquestra/views.py
orquestra/static/orquestra.css
orquestra/static/orquestra.js
orquestra/static/semantic-ui/package.js
orquestra/static/semantic-ui/semantic.css
orquestra/static/semantic-ui/semantic.js
orquestra/static/semantic-ui/semantic.min.css
orquestra/static/semantic-ui/semantic.min.js
orquestra/static/semantic-ui/components/accordion.css
orquestra/static/semantic-ui/components/accordion.js
orquestra/static/semantic-ui/components/accordion.min.css
orquestra/static/semantic-ui/components/accordion.min.js
orquestra/static/semantic-ui/components/ad.css
orquestra/static/semantic-ui/components/ad.min.css
orquestra/static/semantic-ui/components/api.js
orquestra/static/semantic-ui/components/api.min.js
orquestra/static/semantic-ui/components/breadcrumb.css
orquestra/static/semantic-ui/components/breadcrumb.min.css
orquestra/static/semantic-ui/components/button.css
orquestra/static/semantic-ui/components/button.min.css
orquestra/static/semantic-ui/components/card.css
orquestra/static/semantic-ui/components/card.min.css
orquestra/static/semantic-ui/components/checkbox.css
orquestra/static/semantic-ui/components/checkbox.js
orquestra/static/semantic-ui/components/checkbox.min.css
orquestra/static/semantic-ui/components/checkbox.min.js
orquestra/static/semantic-ui/components/colorize.js
orquestra/static/semantic-ui/components/colorize.min.js
orquestra/static/semantic-ui/components/comment.css
orquestra/static/semantic-ui/components/comment.min.css
orquestra/static/semantic-ui/components/container.css
orquestra/static/semantic-ui/components/container.min.css
orquestra/static/semantic-ui/components/dimmer.css
orquestra/static/semantic-ui/components/dimmer.js
orquestra/static/semantic-ui/components/dimmer.min.css
orquestra/static/semantic-ui/components/dimmer.min.js
Orquestra-1.4.dist-info/METADATA
Orquestra-1.4.dist-info/WHEEL
Orquestra-1.4.dist-info/top_level.txt
Orquestra-1.4.dist-info/RECORD
